ShynaGreetings/ShynaGreetings.py
ShynaGreetings/__init__.py
ShynaGreetings-0.0.1.dist-info/LICENSE
ShynaGreetings-0.0.1.dist-info/METADATA
ShynaGreetings-0.0.1.dist-info/WHEEL
ShynaGreetings-0.0.1.dist-info/top_level.txt
ShynaGreetings-0.0.1.dist-info/RECORD
