Metadata-Version: 2.1
Name: ShynaGreetings
Version: 0.0.1
Summary: This package will provide Greetings messages as per request..
Author: Shivam Sharma
Author-email: shivamsharma1913@gmail.com
License-File: LICENSE
Requires-Dist: requests
Requires-Dist: setuptools
Requires-Dist: wheel
